src/pcounter.v
module pcounter
#(
    parameter WIDTH = 4
)
(
    input                  rst_i,
    input                  clk_i,
    input                  en_i,

    output reg [WIDTH-1:0] value_o
);

    reg [WIDTH-1:0] enables;
    wire [WIDTH-1:0] w_en;

    assign w_en = {enables, en_i};

    
    genvar i;
    generate
    for(i=0; i<WIDTH; i=i+1) begin : bit

        always@(posedge rst_i or posedge clk_i)
            if(rst_i) 
                value_o[i] <= 0; 
            else 
                if (w_en[i]) value_o[i] <= ~value_o[i];

        always@(posedge rst_i or posedge clk_i)
            if (rst_i)
                enables[i] <= 0;
            else
                enables[i] <= value_o[i] & w_en[i];
    
    end
    endgenerate
endmodule

tb/tb_pcounter.v
`timescale 1ns/1ns

module clkgen;
    reg clk;

    initial begin
        clk=0;
        forever #(100) clk = ~clk;
    end
endmodule


module tb;
    reg rst;
    reg en;
    clkgen g1();

    pcounter 
    #(.WIDTH(6))
    u1(
        .rst_i(rst),
        .clk_i(g1.clk),
        .en_i(en)
    );


    initial begin
        $dumpfile("pcounter.vcd");
        $dumpvars(0, tb.u1);
    end

    initial begin
        rst = 1;
        en  = 1;
#(350)
        rst = 0;

#(8000)
        en = 0;
#(8000)
        en = 1;
#(8000)
        
        $finish;
    end

endmodule

pcounter.vcd
$date
	Wed Mar 21 17:47:35 2018
$end
$version
	Icarus Verilog
$end
$timescale
	1ns
$end
$scope module tb $end
$scope module u1 $end
$var wire 1 ! clk_i $end
$var wire 1 " en_i $end
$var wire 1 # rst_i $end
$var wire 6 $ w_en [5:0] $end
$var reg 6 % enables [5:0] $end
$var reg 6 & value_o [5:0] $end
$scope begin bit[0] $end
$upscope $end
$scope begin bit[1] $end
$upscope $end
$scope begin bit[2] $end
$upscope $end
$scope begin bit[3] $end
$upscope $end
$scope begin bit[4] $end
$upscope $end
$scope begin bit[5] $end
$upscope $end
$upscope $end
$upscope $end
$enddefinitions $end
#0
$dumpvars
b0 &
b0 %
b1 $
1#
1"
0!
$end
#100
1!
#200
0!
#300
1!
#350
0#
#400
0!
#500
b1 &
1!
#600
0!
#700
b11 $
b0 &
b1 %
1!
#800
0!
#900
b1 $
b0 %
b11 &
1!
#1000
0!
#1100
b11 $
b10 &
b1 %
1!
#1200
0!
#1300
b101 $
b10 %
b1 &
1!
#1400
0!
#1500
b11 $
b1 %
b100 &
1!
#1600
0!
#1700
b1 $
b0 %
b111 &
1!
#1800
0!
#1900
b11 $
b110 &
b1 %
1!
#2000
0!
#2100
b101 $
b10 %
b101 &
1!
#2200
0!
#2300
b1011 $
b0 &
b101 %
1!
#2400
0!
#2500
b1 $
b0 %
b1011 &
1!
#2600
0!
#2700
b11 $
b1010 &
b1 %
1!
#2800
0!
#2900
b101 $
b10 %
b1001 &
1!
#3000
0!
#3100
b11 $
b1 %
b1100 &
1!
#3200
0!
#3300
b1 $
b0 %
b1111 &
1!
#3400
0!
#3500
b11 $
b1110 &
b1 %
1!
#3600
0!
#3700
b101 $
b10 %
b1101 &
1!
#3800
0!
#3900
b1011 $
b1000 &
b101 %
1!
#4000
0!
#4100
b10001 $
b1000 %
b11 &
1!
#4200
0!
#4300
b11 $
b1 %
b10010 &
1!
#4400
0!
#4500
b101 $
b10 %
b10001 &
1!
#4600
0!
#4700
b11 $
b1 %
b10100 &
1!
#4800
0!
#4900
b1 $
b0 %
b10111 &
1!
#5000
0!
#5100
b11 $
b10110 &
b1 %
1!
#5200
0!
#5300
b101 $
b10 %
b10101 &
1!
#5400
0!
#5500
b1011 $
b10000 &
b101 %
1!
#5600
0!
#5700
b1 $
b0 %
b11011 &
1!
#5800
0!
#5900
b11 $
b11010 &
b1 %
1!
#6000
0!
#6100
b101 $
b10 %
b11001 &
1!
#6200
0!
#6300
b11 $
b1 %
b11100 &
1!
#6400
0!
#6500
b1 $
b0 %
b11111 &
1!
#6600
0!
#6700
b11 $
b11110 &
b1 %
1!
#6800
0!
#6900
b101 $
b10 %
b11101 &
1!
#7000
0!
#7100
b1011 $
b11000 &
b101 %
1!
#7200
0!
#7300
b10001 $
b1000 %
b10011 &
1!
#7400
0!
#7500
b100011 $
b10 &
b10001 %
1!
#7600
0!
#7700
b101 $
b10 %
b100001 &
1!
#7800
0!
#7900
b11 $
b1 %
b100100 &
1!
#8000
0!
#8100
b1 $
b0 %
b100111 &
1!
#8200
0!
#8300
b11 $
b100110 &
b1 %
1!
#8350
b10 $
0"
#8400
0!
#8500
b100 $
b100100 &
b10 %
1!
#8600
0!
#8700
b1000 $
b100000 &
b100 %
1!
#8800
0!
#8900
b0 $
b101000 &
b0 %
1!
